scrapyish/__init__.py
scrapyish/crawler.py
scrapyish/http.py
scrapyish/spider.py
Scrapyish-0.1.0.dist-info/LICENSE
Scrapyish-0.1.0.dist-info/METADATA
Scrapyish-0.1.0.dist-info/WHEEL
Scrapyish-0.1.0.dist-info/top_level.txt
Scrapyish-0.1.0.dist-info/RECORD
