Metadata-Version: 2.1
Name: Scrapyish
Version: 0.1.0
Summary: A high-level dynamic web content crawling and web scraping framework
Author-email: alexpdev <alexpdev@pm.me>
License: Apache License
Project-URL: homepage, https://github.com/alexpdev/scrapyish
Project-URL: repository, https://github.com
Project-URL: documentation, https://alexpdev.github.io/scrapyish
Project-URL: changelog, https://alexpdev.github.io/scrapyish/changelog/
Project-URL: issues, https://github.com/alexpdev/scrapyish/issues
Keywords: web-crawler,web-scraping,CLI
Classifier: Environment :: Console
Classifier: Development Status :: 4 - Beta
Classifier: Framework :: Scrapy
Classifier: Operating System :: OS Independent
Classifier: Programming Language :: Python
Classifier: Programming Language :: Python :: 3
Classifier: Programming Language :: Python :: 3.6
Classifier: Programming Language :: Python :: 3.7
Classifier: Programming Language :: Python :: 3.8
Classifier: Programming Language :: Python :: 3.9
Classifier: Programming Language :: Python :: 3.10
Classifier: Programming Language :: Python :: 3 :: Only
Classifier: Intended Audience :: Developers
Classifier: Topic :: Internet :: WWW/HTTP
Classifier: Topic :: Software Development :: Libraries :: Application Frameworks
Classifier: Topic :: Software Development :: Libraries :: Python Modules
Classifier: License :: OSI Approved :: Apache Software License
Requires-Python: >=3.6
License-File: LICENSE
Requires-Dist: playwright
Requires-Dist: setuptools
Requires-Dist: parsel
Requires-Dist: wheel
